{
    "@context": "/contexts/Card",
    "@id": "/cards/ALT_COREKS_B_AX_19_U_358",
    "@type": "Card",
    "allImagePath": {
        "fr-fr": "https://altered-prod-eu.s3.amazonaws.com/Art/COREKS/CARDS/ALT_CORE_B_AX_19/UNIQUE/JPG/fr_FR/3f409c01020369148a0fe7ca7475cfa6.jpg",
        "es-es": "https://altered-prod-eu.s3.amazonaws.com/Art/COREKS/CARDS/ALT_CORE_B_AX_19/UNIQUE/JPG/es_ES/a022fa5efa52f5cb5582a3fb55da24ea.jpg",
        "it-it": "https://altered-prod-eu.s3.amazonaws.com/Art/COREKS/CARDS/ALT_CORE_B_AX_19/UNIQUE/JPG/it_IT/39f1367db3b4485bf54bfd2d241ac989.jpg",
        "de-de": "https://altered-prod-eu.s3.amazonaws.com/Art/COREKS/CARDS/ALT_CORE_B_AX_19/UNIQUE/JPG/de_DE/70c39f649c72f90f2168257be34e2c04.jpg",
        "en-us": "https://altered-prod-eu.s3.amazonaws.com/Art/COREKS/CARDS/ALT_CORE_B_AX_19/UNIQUE/JPG/en_US/f24d5efe4828bab365fe768c37f9cdf5.jpg"
    },
    "assets": {
        "WEB": [
            "https://altered-prod-eu.s3.amazonaws.com/Art/CORE/CARDS/ALT_CORE_B_AX_19/ALT_CORE_B_AX_19_C_WEB.jpg",
            "https://altered-prod-eu.s3.amazonaws.com/Art/CORE/CARDS/ALT_CORE_B_AX_19/ALT_CORE_B_AX_19_R_WEB.jpg",
            "https://altered-prod-eu.s3.amazonaws.com/Art/CORE/CARDS/ALT_CORE_B_AX_19/ALT_CORE_B_AX_19_U_WEB.jpg"
        ]
    },
    "cardRulings": [],
    "cardSet": {
        "@id": "/card_sets/COREKS",
        "@type": "CardSet",
        "id": "01HN5TWSSVYM93FHCEC3K8NNCM",
        "reference": "COREKS",
        "name": "Beyond the Gates - KS Edition"
    },
    "cardSubTypes": [
        {
            "@type": "CardSubType",
            "@id": "/.well-known/genid/aa203559a5c49ba97d29",
            "reference": "DEITY",
            "id": "01HKAGPAJFS4YDQVKY6AB16614",
            "name": "Deity"
        }
    ],
    "cardType": {
        "@id": "/card_types/01H19NWA92A4ERAC4ATMSZNASS",
        "@type": "CardType",
        "reference": "CHARACTER",
        "id": "01H19NWA92A4ERAC4ATMSZNASS",
        "name": "Character"
    },
    "elements": {
        "MAIN_COST": "5",
        "RECALL_COST": "6",
        "MOUNTAIN_POWER": "3",
        "OCEAN_POWER": "5",
        "FOREST_POWER": "3",
        "MAIN_EFFECT": "{J} []For each Permanent you control, you may activate its\u00a0{j} abilities.  {R} []You may have target Character other than me lose [[Fleeting]] and gain 1 boost.",
        "ECHO_EFFECT": "{D} : []You may return a card from your Reserve to your hand."
    },
    "id": "4T98JVJXWN8ZQBPBZPDVP1B6J9",
    "imagePath": "https://altered-prod-eu.s3.amazonaws.com/Art/COREKS/CARDS/ALT_CORE_B_AX_19/JPG/en_EN/a89556c8afc98260b5e17f7e8eb1b1f2.jpg",
    "isSuspended": false,
    "loreEntries": [],
    "lowerPrice": 0,
    "mainFaction": {
        "@id": "/factions/AX",
        "@type": "Faction",
        "reference": "AX",
        "color": "#8c432a",
        "id": "01GE7AC9XBG707G19F03A95TH1",
        "name": "Axiom"
    },
    "name": "Ganesha",
    "qrUrlDetail": "https://qr.altered.gg/ALT_COREKS_B_AX_19_U_358",
    "rarity": {
        "@id": "/rarities/UNIQUE",
        "@type": "Rarity",
        "reference": "UNIQUE",
        "id": "01GE7AC9X35JXEQZJBBD6E4BKW",
        "name": "Unique"
    },
    "reference": "ALT_COREKS_B_AX_19_U_358",
    "translations": {
        "fr-fr": {
            "@context": "/contexts/Card",
            "@id": "/cards/ALT_COREKS_B_AX_19_U_358",
            "@type": "Card",
            "allImagePath": {
                "fr-fr": "https://altered-prod-eu.s3.amazonaws.com/Art/COREKS/CARDS/ALT_CORE_B_AX_19/UNIQUE/JPG/fr_FR/3f409c01020369148a0fe7ca7475cfa6.jpg",
                "es-es": "https://altered-prod-eu.s3.amazonaws.com/Art/COREKS/CARDS/ALT_CORE_B_AX_19/UNIQUE/JPG/es_ES/a022fa5efa52f5cb5582a3fb55da24ea.jpg",
                "it-it": "https://altered-prod-eu.s3.amazonaws.com/Art/COREKS/CARDS/ALT_CORE_B_AX_19/UNIQUE/JPG/it_IT/39f1367db3b4485bf54bfd2d241ac989.jpg",
                "de-de": "https://altered-prod-eu.s3.amazonaws.com/Art/COREKS/CARDS/ALT_CORE_B_AX_19/UNIQUE/JPG/de_DE/70c39f649c72f90f2168257be34e2c04.jpg",
                "en-us": "https://altered-prod-eu.s3.amazonaws.com/Art/COREKS/CARDS/ALT_CORE_B_AX_19/UNIQUE/JPG/en_US/f24d5efe4828bab365fe768c37f9cdf5.jpg"
            },
            "assets": {
                "WEB": [
                    "https://altered-prod-eu.s3.amazonaws.com/Art/CORE/CARDS/ALT_CORE_B_AX_19/ALT_CORE_B_AX_19_C_WEB.jpg",
                    "https://altered-prod-eu.s3.amazonaws.com/Art/CORE/CARDS/ALT_CORE_B_AX_19/ALT_CORE_B_AX_19_R_WEB.jpg",
                    "https://altered-prod-eu.s3.amazonaws.com/Art/CORE/CARDS/ALT_CORE_B_AX_19/ALT_CORE_B_AX_19_U_WEB.jpg"
                ]
            },
            "cardRulings": [],
            "cardSet": {
                "@id": "/card_sets/COREKS",
                "@type": "CardSet",
                "id": "01HN5TWSSVYM93FHCEC3K8NNCM",
                "reference": "COREKS",
                "name": "Au-del\u00e0 des portes - \u00c9dition KS"
            },
            "cardSubTypes": [
                {
                    "@type": "CardSubType",
                    "@id": "/.well-known/genid/6097bb31e10b7f8ad9c6",
                    "reference": "DEITY",
                    "id": "01HKAGPAJFS4YDQVKY6AB16614",
                    "name": "Divinit\u00e9"
                }
            ],
            "cardType": {
                "@id": "/card_types/01H19NWA92A4ERAC4ATMSZNASS",
                "@type": "CardType",
                "reference": "CHARACTER",
                "id": "01H19NWA92A4ERAC4ATMSZNASS",
                "name": "Personnage"
            },
            "elements": {
                "MAIN_COST": "5",
                "RECALL_COST": "6",
                "MOUNTAIN_POWER": "3",
                "OCEAN_POWER": "5",
                "FOREST_POWER": "3",
                "MAIN_EFFECT": "{J} []Pour chaque Permanent que vous contr\u00f4lez, vous pouvez activer ses capacit\u00e9s\u00a0{j}.  {R} []Vous pouvez faire perdre [[Fugace]] et gagner 1\u00a0boost \u00e0 un Personnage cibl\u00e9 autre que moi.",
                "ECHO_EFFECT": "{D}\u00a0: []Vous pouvez renvoyer une carte de votre R\u00e9serve dans votre main."
            },
            "id": "4T98JVJXWN8ZQBPBZPDVP1B6J9",
            "imagePath": "https://altered-prod-eu.s3.amazonaws.com/Art/COREKS/CARDS/ALT_CORE_B_AX_19/UNIQUE/JPG/fr_FR/3f409c01020369148a0fe7ca7475cfa6.jpg",
            "isSuspended": false,
            "loreEntries": [],
            "lowerPrice": 0,
            "mainFaction": {
                "@id": "/factions/AX",
                "@type": "Faction",
                "reference": "AX",
                "color": "#8c432a",
                "id": "01GE7AC9XBG707G19F03A95TH1",
                "name": "Axiom"
            },
            "name": "Ganesh",
            "qrUrlDetail": "https://qr.altered.gg/ALT_COREKS_B_AX_19_U_358",
            "rarity": {
                "@id": "/rarities/UNIQUE",
                "@type": "Rarity",
                "reference": "UNIQUE",
                "id": "01GE7AC9X35JXEQZJBBD6E4BKW",
                "name": "Unique"
            },
            "reference": "ALT_COREKS_B_AX_19_U_358"
        }
    }
}