{
    "@context": "/contexts/Card",
    "@id": "/cards/ALT_CORE_B_LY_20_U_6209",
    "@type": "Card",
    "allImagePath": {
        "de-de": "https://altered-prod-eu.s3.amazonaws.com/Art/CORE/CARDS/ALT_CORE_B_LY_20/UNIQUE/JPG/de_DE/3e01d70f1ee3b262e3409e7f6599bbcf.jpg",
        "en-us": "https://altered-prod-eu.s3.amazonaws.com/Art/CORE/CARDS/ALT_CORE_B_LY_20/UNIQUE/JPG/en_US/79382d6b7eda8dae44739c4fb1e21673.jpg",
        "es-es": "https://altered-prod-eu.s3.amazonaws.com/Art/CORE/CARDS/ALT_CORE_B_LY_20/UNIQUE/JPG/es_ES/f721bc11b364cf92e4855f9ec279e004.jpg",
        "fr-fr": "https://altered-prod-eu.s3.amazonaws.com/Art/CORE/CARDS/ALT_CORE_B_LY_20/UNIQUE/JPG/fr_FR/d5644b7c9498a600e75a1bd23148fca7.jpg",
        "it-it": "https://altered-prod-eu.s3.amazonaws.com/Art/CORE/CARDS/ALT_CORE_B_LY_20/UNIQUE/JPG/it_IT/e88aafc34058513b5c6a6af5e80a73be.jpg"
    },
    "assets": {
        "WEB": [
            "https://altered-prod-eu.s3.amazonaws.com/Art/CORE/CARDS/ALT_CORE_B_LY_20/ALT_CORE_B_LY_20_C_WEB.jpg",
            "https://altered-prod-eu.s3.amazonaws.com/Art/CORE/CARDS/ALT_CORE_B_LY_20/ALT_CORE_B_LY_20_R_WEB.jpg",
            "https://altered-prod-eu.s3.amazonaws.com/Art/CORE/CARDS/ALT_CORE_B_LY_20/ALT_CORE_B_LY_20_U_WEB.jpg"
        ]
    },
    "cardRulings": [],
    "cardSet": {
        "@id": "/card_sets/CORE",
        "@type": "CardSet",
        "id": "01HKAFJN3HG3TWKYV0E014K01G",
        "name": "Beyond the Gates",
        "reference": "CORE"
    },
    "cardSubTypes": [
        {
            "@id": "/.well-known/genid/19efdba49593ee2e60e3",
            "@type": "CardSubType",
            "id": "01HKAGPAJFS4YDQVKY6AB16614",
            "name": "Deity",
            "reference": "DEITY"
        }
    ],
    "cardType": {
        "@id": "/card_types/01H19NWA92A4ERAC4ATMSZNASS",
        "@type": "CardType",
        "id": "01H19NWA92A4ERAC4ATMSZNASS",
        "name": "Character",
        "reference": "CHARACTER"
    },
    "elements": {
        "ECHO_EFFECT": "{D} : []The next Character you play this turn loses [[Fleeting]].",
        "FOREST_POWER": "5",
        "MAIN_COST": "4",
        "MAIN_EFFECT": "{R} If you control two or more [[Boosted]] Characters: Roll a die. On a 4+, I gain [[Anchored]]. On a 1-3, I gain 3 boosts.",
        "MOUNTAIN_POWER": "5",
        "OCEAN_POWER": "4",
        "RECALL_COST": "4"
    },
    "id": "0TS7H6GJ6R9NE8CFNBEETB73JR",
    "imagePath": "https://altered-prod-eu.s3.amazonaws.com/Art/CORE/CARDS/ALT_CORE_B_LY_20/JPG/en_EN/0ed9a04e4d6dc3be7817b7df035fd148.jpg",
    "isSuspended": false,
    "loreEntries": [],
    "lowerPrice": 0,
    "mainFaction": {
        "@id": "/factions/BR",
        "@type": "Faction",
        "color": "#c32637",
        "id": "01GE7AC9WY6PK56RADXXD6P1T4",
        "name": "Bravos",
        "reference": "BR"
    },
    "name": "Asmodeus",
    "qrUrlDetail": "https://qr.altered.gg/ALT_CORE_B_LY_20_U_6209",
    "rarity": {
        "@id": "/rarities/UNIQUE",
        "@type": "Rarity",
        "id": "01GE7AC9X35JXEQZJBBD6E4BKW",
        "name": "Unique",
        "reference": "UNIQUE"
    },
    "reference": "ALT_CORE_B_LY_20_U_6209",
    "translations": {
        "fr-fr": {
            "@context": "/contexts/Card",
            "@id": "/cards/ALT_CORE_B_LY_20_U_6209",
            "@type": "Card",
            "allImagePath": {
                "de-de": "https://altered-prod-eu.s3.amazonaws.com/Art/CORE/CARDS/ALT_CORE_B_LY_20/UNIQUE/JPG/de_DE/3e01d70f1ee3b262e3409e7f6599bbcf.jpg",
                "en-us": "https://altered-prod-eu.s3.amazonaws.com/Art/CORE/CARDS/ALT_CORE_B_LY_20/UNIQUE/JPG/en_US/79382d6b7eda8dae44739c4fb1e21673.jpg",
                "es-es": "https://altered-prod-eu.s3.amazonaws.com/Art/CORE/CARDS/ALT_CORE_B_LY_20/UNIQUE/JPG/es_ES/f721bc11b364cf92e4855f9ec279e004.jpg",
                "fr-fr": "https://altered-prod-eu.s3.amazonaws.com/Art/CORE/CARDS/ALT_CORE_B_LY_20/UNIQUE/JPG/fr_FR/d5644b7c9498a600e75a1bd23148fca7.jpg",
                "it-it": "https://altered-prod-eu.s3.amazonaws.com/Art/CORE/CARDS/ALT_CORE_B_LY_20/UNIQUE/JPG/it_IT/e88aafc34058513b5c6a6af5e80a73be.jpg"
            },
            "assets": {
                "WEB": [
                    "https://altered-prod-eu.s3.amazonaws.com/Art/CORE/CARDS/ALT_CORE_B_LY_20/ALT_CORE_B_LY_20_C_WEB.jpg",
                    "https://altered-prod-eu.s3.amazonaws.com/Art/CORE/CARDS/ALT_CORE_B_LY_20/ALT_CORE_B_LY_20_R_WEB.jpg",
                    "https://altered-prod-eu.s3.amazonaws.com/Art/CORE/CARDS/ALT_CORE_B_LY_20/ALT_CORE_B_LY_20_U_WEB.jpg"
                ]
            },
            "cardRulings": [],
            "cardSet": {
                "@id": "/card_sets/CORE",
                "@type": "CardSet",
                "id": "01HKAFJN3HG3TWKYV0E014K01G",
                "name": "Au-delà des portes",
                "reference": "CORE"
            },
            "cardSubTypes": [
                {
                    "@id": "/.well-known/genid/91f1e3f75e5937f9de0b",
                    "@type": "CardSubType",
                    "id": "01HKAGPAJFS4YDQVKY6AB16614",
                    "name": "Divinité",
                    "reference": "DEITY"
                }
            ],
            "cardType": {
                "@id": "/card_types/01H19NWA92A4ERAC4ATMSZNASS",
                "@type": "CardType",
                "id": "01H19NWA92A4ERAC4ATMSZNASS",
                "name": "Personnage",
                "reference": "CHARACTER"
            },
            "elements": {
                "ECHO_EFFECT": "{D} : []Le prochain Personnage que vous jouez ce tour perd [[Fugace]].",
                "FOREST_POWER": "5",
                "MAIN_COST": "4",
                "MAIN_EFFECT": "{R} Si vous contrôlez au moins deux Personnages [[Boostés]] : Lancez un dé. Sur 4+, je gagne [[Ancré]]. Sur 1-3, je gagne 3 boosts.",
                "MOUNTAIN_POWER": "5",
                "OCEAN_POWER": "4",
                "RECALL_COST": "4"
            },
            "id": "0TS7H6GJ6R9NE8CFNBEETB73JR",
            "imagePath": "https://altered-prod-eu.s3.amazonaws.com/Art/CORE/CARDS/ALT_CORE_B_LY_20/UNIQUE/JPG/fr_FR/d5644b7c9498a600e75a1bd23148fca7.jpg",
            "isSuspended": false,
            "loreEntries": [],
            "lowerPrice": 0,
            "mainFaction": {
                "@id": "/factions/BR",
                "@type": "Faction",
                "color": "#c32637",
                "id": "01GE7AC9WY6PK56RADXXD6P1T4",
                "name": "Bravos",
                "reference": "BR"
            },
            "name": "Asmodée",
            "qrUrlDetail": "https://qr.altered.gg/ALT_CORE_B_LY_20_U_6209",
            "rarity": {
                "@id": "/rarities/UNIQUE",
                "@type": "Rarity",
                "id": "01GE7AC9X35JXEQZJBBD6E4BKW",
                "name": "Unique",
                "reference": "UNIQUE"
            },
            "reference": "ALT_CORE_B_LY_20_U_6209"
        }
    }
}