{
    "@context": "\/contexts\/Card",
    "@id": "\/cards\/ALT_CORE_B_OR_14_U_4646",
    "@type": "Card",
    "allImagePath": {
        "fr-fr": "https:\/\/altered-prod-eu.s3.amazonaws.com\/Art\/CORE\/CARDS\/ALT_CORE_B_OR_14\/UNIQUE\/JPG\/fr_FR\/067d3319d71c34c2fa583082d08a6a80.jpg",
        "es-es": "https:\/\/altered-prod-eu.s3.amazonaws.com\/Art\/CORE\/CARDS\/ALT_CORE_B_OR_14\/UNIQUE\/JPG\/es_ES\/923569b0ac867f31e32be94574ec895d.jpg",
        "it-it": "https:\/\/altered-prod-eu.s3.amazonaws.com\/Art\/CORE\/CARDS\/ALT_CORE_B_OR_14\/UNIQUE\/JPG\/it_IT\/066ea25db47bd47e3a61e07dda3f5d3f.jpg",
        "de-de": "https:\/\/altered-prod-eu.s3.amazonaws.com\/Art\/CORE\/CARDS\/ALT_CORE_B_OR_14\/UNIQUE\/JPG\/de_DE\/855f0e2193688ad3521a461743c78bbf.jpg",
        "en-us": "https:\/\/altered-prod-eu.s3.amazonaws.com\/Art\/CORE\/CARDS\/ALT_CORE_B_OR_14\/UNIQUE\/JPG\/en_US\/e4440b7611affabcec320073af869f9b.jpg"
    },
    "assets": {
        "WEB": [
            "https:\/\/altered-prod-eu.s3.amazonaws.com\/Art\/CORE\/CARDS\/ALT_CORE_B_OR_14\/ALT_CORE_B_OR_14_C_WEB.jpg",
            "https:\/\/altered-prod-eu.s3.amazonaws.com\/Art\/CORE\/CARDS\/ALT_CORE_B_OR_14\/ALT_CORE_B_OR_14_R_WEB.jpg",
            "https:\/\/altered-prod-eu.s3.amazonaws.com\/Art\/CORE\/CARDS\/ALT_CORE_B_OR_14\/ALT_CORE_B_OR_14_U_WEB.jpg"
        ]
    },
    "cardRulings": [],
    "cardSet": {
        "@id": "\/card_sets\/CORE",
        "@type": "CardSet",
        "id": "01HKAFJN3HG3TWKYV0E014K01G",
        "reference": "CORE",
        "name": "Beyond the Gates"
    },
    "cardSubTypes": [
        {
            "@type": "CardSubType",
            "@id": "\/.well-known\/genid\/f0d5d11bb784cf28e951",
            "reference": "CITIZEN",
            "id": "01HKAGQWDFDGS8YVZGW98BVV9D",
            "name": "Citizen"
        }
    ],
    "cardType": {
        "@id": "\/card_types\/01H19NWA92A4ERAC4ATMSZNASS",
        "@type": "CardType",
        "reference": "CHARACTER",
        "id": "01H19NWA92A4ERAC4ATMSZNASS",
        "name": "Character"
    },
    "elements": {
        "MAIN_COST": "3",
        "RECALL_COST": "3",
        "MOUNTAIN_POWER": "3",
        "OCEAN_POWER": "1",
        "FOREST_POWER": "3",
        "MAIN_EFFECT": "{J} You may discard a card from your Reserve. If you do: [Sabotage].  At Dusk\u00a0\u2014 If you control two or more [[Boosted]] Characters: [Sabotage].",
        "ECHO_EFFECT": "{D} : []You may have target Character gain [[Fleeting]]."
    },
    "id": "325HDFH8149E98GXJETTQGE43E",
    "imagePath": "https:\/\/altered-prod-eu.s3.amazonaws.com\/Art\/CORE\/CARDS\/ALT_CORE_B_OR_14\/JPG\/en_EN\/8bf7d53f9d0b4a0365ccd198e21355d2.jpg",
    "isSuspended": false,
    "loreEntries": [],
    "lowerPrice": 0,
    "mainFaction": {
        "@id": "\/factions\/BR",
        "@type": "Faction",
        "reference": "BR",
        "color": "#c32637",
        "id": "01GE7AC9WY6PK56RADXXD6P1T4",
        "name": "Bravos"
    },
    "name": "Ordis Spy",
    "qrUrlDetail": "https:\/\/qr.altered.gg\/ALT_CORE_B_OR_14_U_4646",
    "rarity": {
        "@id": "\/rarities\/UNIQUE",
        "@type": "Rarity",
        "reference": "UNIQUE",
        "id": "01GE7AC9X35JXEQZJBBD6E4BKW",
        "name": "Unique"
    },
    "reference": "ALT_CORE_B_OR_14_U_4646",
    "translations": {
        "fr-fr": {
            "@context": "\/contexts\/Card",
            "@id": "\/cards\/ALT_CORE_B_OR_14_U_4646",
            "@type": "Card",
            "allImagePath": {
                "fr-fr": "https:\/\/altered-prod-eu.s3.amazonaws.com\/Art\/CORE\/CARDS\/ALT_CORE_B_OR_14\/UNIQUE\/JPG\/fr_FR\/067d3319d71c34c2fa583082d08a6a80.jpg",
                "es-es": "https:\/\/altered-prod-eu.s3.amazonaws.com\/Art\/CORE\/CARDS\/ALT_CORE_B_OR_14\/UNIQUE\/JPG\/es_ES\/923569b0ac867f31e32be94574ec895d.jpg",
                "it-it": "https:\/\/altered-prod-eu.s3.amazonaws.com\/Art\/CORE\/CARDS\/ALT_CORE_B_OR_14\/UNIQUE\/JPG\/it_IT\/066ea25db47bd47e3a61e07dda3f5d3f.jpg",
                "de-de": "https:\/\/altered-prod-eu.s3.amazonaws.com\/Art\/CORE\/CARDS\/ALT_CORE_B_OR_14\/UNIQUE\/JPG\/de_DE\/855f0e2193688ad3521a461743c78bbf.jpg",
                "en-us": "https:\/\/altered-prod-eu.s3.amazonaws.com\/Art\/CORE\/CARDS\/ALT_CORE_B_OR_14\/UNIQUE\/JPG\/en_US\/e4440b7611affabcec320073af869f9b.jpg"
            },
            "assets": {
                "WEB": [
                    "https:\/\/altered-prod-eu.s3.amazonaws.com\/Art\/CORE\/CARDS\/ALT_CORE_B_OR_14\/ALT_CORE_B_OR_14_C_WEB.jpg",
                    "https:\/\/altered-prod-eu.s3.amazonaws.com\/Art\/CORE\/CARDS\/ALT_CORE_B_OR_14\/ALT_CORE_B_OR_14_R_WEB.jpg",
                    "https:\/\/altered-prod-eu.s3.amazonaws.com\/Art\/CORE\/CARDS\/ALT_CORE_B_OR_14\/ALT_CORE_B_OR_14_U_WEB.jpg"
                ]
            },
            "cardRulings": [],
            "cardSet": {
                "@id": "\/card_sets\/CORE",
                "@type": "CardSet",
                "id": "01HKAFJN3HG3TWKYV0E014K01G",
                "reference": "CORE",
                "name": "Au-del\u00e0 des portes"
            },
            "cardSubTypes": [
                {
                    "@type": "CardSubType",
                    "@id": "\/.well-known\/genid\/267b5b8a322a41c92a34",
                    "reference": "CITIZEN",
                    "id": "01HKAGQWDFDGS8YVZGW98BVV9D",
                    "name": "Citoyen"
                }
            ],
            "cardType": {
                "@id": "\/card_types\/01H19NWA92A4ERAC4ATMSZNASS",
                "@type": "CardType",
                "reference": "CHARACTER",
                "id": "01H19NWA92A4ERAC4ATMSZNASS",
                "name": "Personnage"
            },
            "elements": {
                "MAIN_COST": "3",
                "RECALL_COST": "3",
                "MOUNTAIN_POWER": "3",
                "OCEAN_POWER": "1",
                "FOREST_POWER": "3",
                "MAIN_EFFECT": "{J} Vous pouvez d\u00e9fausser une carte de votre R\u00e9serve. Si vous le faites\u00a0: [Sabotez].  Au Cr\u00e9puscule\u00a0\u2014 Si vous contr\u00f4lez au moins deux Personnages [[Boost\u00e9s]]\u00a0: [Sabotez].",
                "ECHO_EFFECT": "{D}\u00a0: []Vous pouvez faire gagner [[Fugace]] \u00e0 un Personnage cibl\u00e9."
            },
            "id": "325HDFH8149E98GXJETTQGE43E",
            "imagePath": "https:\/\/altered-prod-eu.s3.amazonaws.com\/Art\/CORE\/CARDS\/ALT_CORE_B_OR_14\/UNIQUE\/JPG\/fr_FR\/067d3319d71c34c2fa583082d08a6a80.jpg",
            "isSuspended": false,
            "loreEntries": [],
            "lowerPrice": 0,
            "mainFaction": {
                "@id": "\/factions\/BR",
                "@type": "Faction",
                "reference": "BR",
                "color": "#c32637",
                "id": "01GE7AC9WY6PK56RADXXD6P1T4",
                "name": "Bravos"
            },
            "name": "Espionne Ordis",
            "qrUrlDetail": "https:\/\/qr.altered.gg\/ALT_CORE_B_OR_14_U_4646",
            "rarity": {
                "@id": "\/rarities\/UNIQUE",
                "@type": "Rarity",
                "reference": "UNIQUE",
                "id": "01GE7AC9X35JXEQZJBBD6E4BKW",
                "name": "Unique"
            },
            "reference": "ALT_CORE_B_OR_14_U_4646"
        }
    }
}