{
    "@context": "/contexts/Card",
    "@id": "/cards/ALT_CORE_B_OR_04_U_6760",
    "@type": "Card",
    "allImagePath": {
        "de-de": "https://altered-prod-eu.s3.amazonaws.com/Art/CORE/CARDS/ALT_CORE_B_OR_04/UNIQUE/JPG/de_DE/0ee06b440d998df972ffd5ff7f6c3c87.jpg",
        "en-us": "https://altered-prod-eu.s3.amazonaws.com/Art/CORE/CARDS/ALT_CORE_B_OR_04/UNIQUE/JPG/en_US/e2243e09fb8c0b1630200926a8565082.jpg",
        "es-es": "https://altered-prod-eu.s3.amazonaws.com/Art/CORE/CARDS/ALT_CORE_B_OR_04/UNIQUE/JPG/es_ES/39afece0c7b81494da3d8db895950257.jpg",
        "fr-fr": "https://altered-prod-eu.s3.amazonaws.com/Art/CORE/CARDS/ALT_CORE_B_OR_04/UNIQUE/JPG/fr_FR/7eca2731099491211203e9be76774d95.jpg",
        "it-it": "https://altered-prod-eu.s3.amazonaws.com/Art/CORE/CARDS/ALT_CORE_B_OR_04/UNIQUE/JPG/it_IT/01b8c5766003faff2a453aa133db80de.jpg"
    },
    "assets": {
        "WEB": [
            "https://altered-prod-eu.s3.amazonaws.com/Art/CORE/CARDS/ALT_CORE_B_OR_04/ALT_CORE_B_OR_04_C_WEB.jpg",
            "https://altered-prod-eu.s3.amazonaws.com/Art/CORE/CARDS/ALT_CORE_B_OR_04/ALT_CORE_B_OR_04_R_WEB.jpg",
            "https://altered-prod-eu.s3.amazonaws.com/Art/CORE/CARDS/ALT_CORE_B_OR_04/ALT_CORE_B_OR_04_U_WEB.jpg"
        ]
    },
    "cardRulings": [],
    "cardSet": {
        "@id": "/card_sets/CORE",
        "@type": "CardSet",
        "id": "01HKAFJN3HG3TWKYV0E014K01G",
        "name": "Beyond the Gates",
        "reference": "CORE"
    },
    "cardSubTypes": [
        {
            "@id": "/.well-known/genid/8f4f92f9beb30ea22ccb",
            "@type": "CardSubType",
            "id": "01HKAGPRRNK7X4TZEBYSPK6DDC",
            "name": "Messenger",
            "reference": "MESSENGER"
        }
    ],
    "cardType": {
        "@id": "/card_types/01H19NWA92A4ERAC4ATMSZNASS",
        "@type": "CardType",
        "id": "01H19NWA92A4ERAC4ATMSZNASS",
        "name": "Character",
        "reference": "CHARACTER"
    },
    "elements": {
        "ECHO_EFFECT": "{D} : []Create an [Ordis Recruit 1/1/1] Soldier token in your Hero Expedition.",
        "FOREST_POWER": "0",
        "MAIN_COST": "2",
        "MAIN_EFFECT": "{J} You may pay {1}. If you do: Create an [Ordis Recruit 1/1/1] Soldier token in my Expedition.  At Dusk — If you control a token: Draw a card.",
        "MOUNTAIN_POWER": "1",
        "OCEAN_POWER": "0",
        "RECALL_COST": "2"
    },
    "id": "351CF72V5M83FSJ4Y16J0AJER0",
    "imagePath": "https://altered-prod-eu.s3.amazonaws.com/Art/CORE/CARDS/ALT_CORE_B_OR_04/JPG/en_EN/91abed9e492f68e68f6cb66a185a1fd9.jpg",
    "isSuspended": false,
    "loreEntries": [],
    "lowerPrice": 0,
    "mainFaction": {
        "@id": "/factions/OR",
        "@type": "Faction",
        "color": "#0f6593",
        "id": "01GE7AC9X78DXSNKNB15KCF69X",
        "name": "Ordis",
        "reference": "OR"
    },
    "name": "Paper Herald",
    "qrUrlDetail": "https://qr.altered.gg/ALT_CORE_B_OR_04_U_6760",
    "rarity": {
        "@id": "/rarities/UNIQUE",
        "@type": "Rarity",
        "id": "01GE7AC9X35JXEQZJBBD6E4BKW",
        "name": "Unique",
        "reference": "UNIQUE"
    },
    "reference": "ALT_CORE_B_OR_04_U_6760",
    "translations": {
        "fr-fr": {
            "@context": "/contexts/Card",
            "@id": "/cards/ALT_CORE_B_OR_04_U_6760",
            "@type": "Card",
            "allImagePath": {
                "de-de": "https://altered-prod-eu.s3.amazonaws.com/Art/CORE/CARDS/ALT_CORE_B_OR_04/UNIQUE/JPG/de_DE/0ee06b440d998df972ffd5ff7f6c3c87.jpg",
                "en-us": "https://altered-prod-eu.s3.amazonaws.com/Art/CORE/CARDS/ALT_CORE_B_OR_04/UNIQUE/JPG/en_US/e2243e09fb8c0b1630200926a8565082.jpg",
                "es-es": "https://altered-prod-eu.s3.amazonaws.com/Art/CORE/CARDS/ALT_CORE_B_OR_04/UNIQUE/JPG/es_ES/39afece0c7b81494da3d8db895950257.jpg",
                "fr-fr": "https://altered-prod-eu.s3.amazonaws.com/Art/CORE/CARDS/ALT_CORE_B_OR_04/UNIQUE/JPG/fr_FR/7eca2731099491211203e9be76774d95.jpg",
                "it-it": "https://altered-prod-eu.s3.amazonaws.com/Art/CORE/CARDS/ALT_CORE_B_OR_04/UNIQUE/JPG/it_IT/01b8c5766003faff2a453aa133db80de.jpg"
            },
            "assets": {
                "WEB": [
                    "https://altered-prod-eu.s3.amazonaws.com/Art/CORE/CARDS/ALT_CORE_B_OR_04/ALT_CORE_B_OR_04_C_WEB.jpg",
                    "https://altered-prod-eu.s3.amazonaws.com/Art/CORE/CARDS/ALT_CORE_B_OR_04/ALT_CORE_B_OR_04_R_WEB.jpg",
                    "https://altered-prod-eu.s3.amazonaws.com/Art/CORE/CARDS/ALT_CORE_B_OR_04/ALT_CORE_B_OR_04_U_WEB.jpg"
                ]
            },
            "cardRulings": [],
            "cardSet": {
                "@id": "/card_sets/CORE",
                "@type": "CardSet",
                "id": "01HKAFJN3HG3TWKYV0E014K01G",
                "name": "Au-delà des portes",
                "reference": "CORE"
            },
            "cardSubTypes": [
                {
                    "@id": "/.well-known/genid/4ed3b29d39aa444e5f16",
                    "@type": "CardSubType",
                    "id": "01HKAGPRRNK7X4TZEBYSPK6DDC",
                    "name": "Émissaire",
                    "reference": "MESSENGER"
                }
            ],
            "cardType": {
                "@id": "/card_types/01H19NWA92A4ERAC4ATMSZNASS",
                "@type": "CardType",
                "id": "01H19NWA92A4ERAC4ATMSZNASS",
                "name": "Personnage",
                "reference": "CHARACTER"
            },
            "elements": {
                "ECHO_EFFECT": "{D} : []Créez un jeton Soldat [1/1/1 Recrue Ordis] dans votre Expédition Héros.",
                "FOREST_POWER": "0",
                "MAIN_COST": "2",
                "MAIN_EFFECT": "{J} Vous pouvez payer {1}. Si vous le faites : Créez un jeton Soldat [1/1/1 Recrue Ordis] dans mon Expédition.  Au Crépuscule — Si vous contrôlez un jeton : Piochez une carte.",
                "MOUNTAIN_POWER": "1",
                "OCEAN_POWER": "0",
                "RECALL_COST": "2"
            },
            "id": "351CF72V5M83FSJ4Y16J0AJER0",
            "imagePath": "https://altered-prod-eu.s3.amazonaws.com/Art/CORE/CARDS/ALT_CORE_B_OR_04/UNIQUE/JPG/fr_FR/7eca2731099491211203e9be76774d95.jpg",
            "isSuspended": false,
            "loreEntries": [],
            "lowerPrice": 0,
            "mainFaction": {
                "@id": "/factions/OR",
                "@type": "Faction",
                "color": "#0f6593",
                "id": "01GE7AC9X78DXSNKNB15KCF69X",
                "name": "Ordis",
                "reference": "OR"
            },
            "name": "Héraut de Papier",
            "qrUrlDetail": "https://qr.altered.gg/ALT_CORE_B_OR_04_U_6760",
            "rarity": {
                "@id": "/rarities/UNIQUE",
                "@type": "Rarity",
                "id": "01GE7AC9X35JXEQZJBBD6E4BKW",
                "name": "Unique",
                "reference": "UNIQUE"
            },
            "reference": "ALT_CORE_B_OR_04_U_6760"
        }
    }
}