{
    "@context": "/contexts/Card",
    "@id": "/cards/ALT_CORE_B_MU_22_U_5019",
    "@type": "Card",
    "allImagePath": {
        "de-de": "https://altered-prod-eu.s3.amazonaws.com/Art/CORE/CARDS/ALT_CORE_B_MU_22/UNIQUE/JPG/de_DE/f1e94d6b303adbf1858e39a904fa57d3.jpg",
        "en-us": "https://altered-prod-eu.s3.amazonaws.com/Art/CORE/CARDS/ALT_CORE_B_MU_22/UNIQUE/JPG/en_US/ad3bc2d0dbe4665fb6dec2218725d1ed.jpg",
        "es-es": "https://altered-prod-eu.s3.amazonaws.com/Art/CORE/CARDS/ALT_CORE_B_MU_22/UNIQUE/JPG/es_ES/2161a5daa19f514f5938129c8b6f9cb3.jpg",
        "fr-fr": "https://altered-prod-eu.s3.amazonaws.com/Art/CORE/CARDS/ALT_CORE_B_MU_22/UNIQUE/JPG/fr_FR/90adbf8ef3686e35d9f246a8861673d0.jpg",
        "it-it": "https://altered-prod-eu.s3.amazonaws.com/Art/CORE/CARDS/ALT_CORE_B_MU_22/UNIQUE/JPG/it_IT/6379e3b7afb09712ccaa76d8e2563baa.jpg"
    },
    "assets": {
        "WEB": [
            "https://altered-prod-eu.s3.amazonaws.com/Art/CORE/CARDS/ALT_CORE_B_MU_22/ALT_CORE_B_MU_22_C_WEB.jpg",
            "https://altered-prod-eu.s3.amazonaws.com/Art/CORE/CARDS/ALT_CORE_B_MU_22/ALT_CORE_B_MU_22_R_WEB.jpg",
            "https://altered-prod-eu.s3.amazonaws.com/Art/CORE/CARDS/ALT_CORE_B_MU_22/ALT_CORE_B_MU_22_U_WEB.jpg"
        ]
    },
    "cardRulings": [],
    "cardSet": {
        "@id": "/card_sets/CORE",
        "@type": "CardSet",
        "id": "01HKAFJN3HG3TWKYV0E014K01G",
        "name": "Beyond the Gates",
        "reference": "CORE"
    },
    "cardSubTypes": [
        {
            "@id": "/.well-known/genid/5357595a945b837e13a0",
            "@type": "CardSubType",
            "id": "01HKAGQCSK17FMGRQDPCFZZ4GB",
            "name": "Dragon",
            "reference": "DRAGON"
        },
        {
            "@id": "/.well-known/genid/011e85ce9cbe54b03bc1",
            "@type": "CardSubType",
            "id": "01HKAGSB49H24XWW17AAY441MT",
            "name": "Plant",
            "reference": "PLANT"
        }
    ],
    "cardType": {
        "@id": "/card_types/01H19NWA92A4ERAC4ATMSZNASS",
        "@type": "CardType",
        "id": "01H19NWA92A4ERAC4ATMSZNASS",
        "name": "Character",
        "reference": "CHARACTER"
    },
    "elements": {
        "FOREST_POWER": "0",
        "MAIN_COST": "7",
        "MAIN_EFFECT": "[][]I am [Eternal].  At Noon — If I have 1 or more boosts: I gain 3 boosts.  When I leave the Expedition zone — You may put a card from your hand in Reserve. If you do: Put the top card of your deck in your Mana zone (as an exhausted Mana Orb).",
        "MOUNTAIN_POWER": "2",
        "OCEAN_POWER": "5",
        "RECALL_COST": "7"
    },
    "id": "4F40KF5M9E9BJ9SA68RK6CF6GP",
    "imagePath": "https://altered-prod-eu.s3.amazonaws.com/Art/CORE/CARDS/ALT_CORE_B_MU_22/JPG/en_EN/80b7bab8c4bc73b76ca8346c6eb4b018.jpg",
    "isSuspended": false,
    "loreEntries": [],
    "lowerPrice": 0,
    "mainFaction": {
        "@id": "/factions/MU",
        "@type": "Faction",
        "color": "#3d6b42",
        "id": "01GE7AC9X2BNM40TTAYAEFSZSJ",
        "name": "Muna",
        "reference": "MU"
    },
    "name": "Hydracaena",
    "qrUrlDetail": "https://qr.altered.gg/ALT_CORE_B_MU_22_U_5019",
    "rarity": {
        "@id": "/rarities/UNIQUE",
        "@type": "Rarity",
        "id": "01GE7AC9X35JXEQZJBBD6E4BKW",
        "name": "Unique",
        "reference": "UNIQUE"
    },
    "reference": "ALT_CORE_B_MU_22_U_5019",
    "translations": {
        "fr-fr": {
            "@context": "/contexts/Card",
            "@id": "/cards/ALT_CORE_B_MU_22_U_5019",
            "@type": "Card",
            "allImagePath": {
                "de-de": "https://altered-prod-eu.s3.amazonaws.com/Art/CORE/CARDS/ALT_CORE_B_MU_22/UNIQUE/JPG/de_DE/f1e94d6b303adbf1858e39a904fa57d3.jpg",
                "en-us": "https://altered-prod-eu.s3.amazonaws.com/Art/CORE/CARDS/ALT_CORE_B_MU_22/UNIQUE/JPG/en_US/ad3bc2d0dbe4665fb6dec2218725d1ed.jpg",
                "es-es": "https://altered-prod-eu.s3.amazonaws.com/Art/CORE/CARDS/ALT_CORE_B_MU_22/UNIQUE/JPG/es_ES/2161a5daa19f514f5938129c8b6f9cb3.jpg",
                "fr-fr": "https://altered-prod-eu.s3.amazonaws.com/Art/CORE/CARDS/ALT_CORE_B_MU_22/UNIQUE/JPG/fr_FR/90adbf8ef3686e35d9f246a8861673d0.jpg",
                "it-it": "https://altered-prod-eu.s3.amazonaws.com/Art/CORE/CARDS/ALT_CORE_B_MU_22/UNIQUE/JPG/it_IT/6379e3b7afb09712ccaa76d8e2563baa.jpg"
            },
            "assets": {
                "WEB": [
                    "https://altered-prod-eu.s3.amazonaws.com/Art/CORE/CARDS/ALT_CORE_B_MU_22/ALT_CORE_B_MU_22_C_WEB.jpg",
                    "https://altered-prod-eu.s3.amazonaws.com/Art/CORE/CARDS/ALT_CORE_B_MU_22/ALT_CORE_B_MU_22_R_WEB.jpg",
                    "https://altered-prod-eu.s3.amazonaws.com/Art/CORE/CARDS/ALT_CORE_B_MU_22/ALT_CORE_B_MU_22_U_WEB.jpg"
                ]
            },
            "cardRulings": [],
            "cardSet": {
                "@id": "/card_sets/CORE",
                "@type": "CardSet",
                "id": "01HKAFJN3HG3TWKYV0E014K01G",
                "name": "Au-delà des portes",
                "reference": "CORE"
            },
            "cardSubTypes": [
                {
                    "@id": "/.well-known/genid/a121b221fd662437ce11",
                    "@type": "CardSubType",
                    "id": "01HKAGQCSK17FMGRQDPCFZZ4GB",
                    "name": "Dragon",
                    "reference": "DRAGON"
                },
                {
                    "@id": "/.well-known/genid/f190447f46b44148633a",
                    "@type": "CardSubType",
                    "id": "01HKAGSB49H24XWW17AAY441MT",
                    "name": "Plante",
                    "reference": "PLANT"
                }
            ],
            "cardType": {
                "@id": "/card_types/01H19NWA92A4ERAC4ATMSZNASS",
                "@type": "CardType",
                "id": "01H19NWA92A4ERAC4ATMSZNASS",
                "name": "Personnage",
                "reference": "CHARACTER"
            },
            "elements": {
                "FOREST_POWER": "0",
                "MAIN_COST": "7",
                "MAIN_EFFECT": "[][]Je suis [Éternel].  À Midi — Si j'ai au moins 1 boost : Je gagne 3 boosts.  Lorsque je quitte la zone d'Expédition — Vous pouvez mettre une carte de votre main en Réserve. Si vous le faites : Mettez la première carte de votre deck dans votre zone de Mana (en tant qu'Orbe de Mana épuisé).",
                "MOUNTAIN_POWER": "2",
                "OCEAN_POWER": "5",
                "RECALL_COST": "7"
            },
            "id": "4F40KF5M9E9BJ9SA68RK6CF6GP",
            "imagePath": "https://altered-prod-eu.s3.amazonaws.com/Art/CORE/CARDS/ALT_CORE_B_MU_22/UNIQUE/JPG/fr_FR/90adbf8ef3686e35d9f246a8861673d0.jpg",
            "isSuspended": false,
            "loreEntries": [],
            "lowerPrice": 0,
            "mainFaction": {
                "@id": "/factions/MU",
                "@type": "Faction",
                "color": "#3d6b42",
                "id": "01GE7AC9X2BNM40TTAYAEFSZSJ",
                "name": "Muna",
                "reference": "MU"
            },
            "name": "Hydracaena",
            "qrUrlDetail": "https://qr.altered.gg/ALT_CORE_B_MU_22_U_5019",
            "rarity": {
                "@id": "/rarities/UNIQUE",
                "@type": "Rarity",
                "id": "01GE7AC9X35JXEQZJBBD6E4BKW",
                "name": "Unique",
                "reference": "UNIQUE"
            },
            "reference": "ALT_CORE_B_MU_22_U_5019"
        }
    }
}