{
    "@context": "/contexts/Card",
    "@id": "/cards/ALT_COREKS_B_BR_12_U_1048",
    "@type": "Card",
    "allImagePath": {
        "de-de": "https://altered-prod-eu.s3.amazonaws.com/Art/COREKS/CARDS/ALT_CORE_B_BR_12/UNIQUE/JPG/de_DE/50e31b0b6566addb1a40c2353b868a11.jpg",
        "en-us": "https://altered-prod-eu.s3.amazonaws.com/Art/COREKS/CARDS/ALT_CORE_B_BR_12/UNIQUE/JPG/en_US/95c041862b1f39955c10527f88fd17ad.jpg",
        "es-es": "https://altered-prod-eu.s3.amazonaws.com/Art/COREKS/CARDS/ALT_CORE_B_BR_12/UNIQUE/JPG/es_ES/f56c7114846926f489cf7f3ab48b48c1.jpg",
        "fr-fr": "https://altered-prod-eu.s3.amazonaws.com/Art/COREKS/CARDS/ALT_CORE_B_BR_12/UNIQUE/JPG/fr_FR/aef78c6c1f744ab16bd8ee07d02ccc69.jpg",
        "it-it": "https://altered-prod-eu.s3.amazonaws.com/Art/COREKS/CARDS/ALT_CORE_B_BR_12/UNIQUE/JPG/it_IT/a5699c3f581021a677b2548b58f6e449.jpg"
    },
    "assets": {
        "WEB": [
            "https://altered-prod-eu.s3.amazonaws.com/Art/CORE/CARDS/ALT_CORE_B_BR_12/ALT_CORE_B_BR_12_C_WEB.jpg",
            "https://altered-prod-eu.s3.amazonaws.com/Art/CORE/CARDS/ALT_CORE_B_BR_12/ALT_CORE_B_BR_12_R_WEB.jpg",
            "https://altered-prod-eu.s3.amazonaws.com/Art/CORE/CARDS/ALT_CORE_B_BR_12/ALT_CORE_B_BR_12_U_WEB.jpg"
        ]
    },
    "cardRulings": [],
    "cardSet": {
        "@id": "/card_sets/COREKS",
        "@type": "CardSet",
        "id": "01HN5TWSSVYM93FHCEC3K8NNCM",
        "name": "Beyond the Gates - KS Edition",
        "reference": "COREKS"
    },
    "cardSubTypes": [
        {
            "@id": "/.well-known/genid/86cbf20f76561b3093fd",
            "@type": "CardSubType",
            "id": "01HKAGPC92CGHANVSRSC8R8ES6",
            "name": "Adventurer",
            "reference": "ADVENTURER"
        }
    ],
    "cardType": {
        "@id": "/card_types/01H19NWA92A4ERAC4ATMSZNASS",
        "@type": "CardType",
        "id": "01H19NWA92A4ERAC4ATMSZNASS",
        "name": "Character",
        "reference": "CHARACTER"
    },
    "elements": {
        "FOREST_POWER": "1",
        "MAIN_COST": "3",
        "MAIN_EFFECT": "{H} You may put a card from your hand in Reserve. If you do: I gain 2 boosts.  At Dusk — If I have 1 or more boosts: I lose [[Fleeting]].",
        "MOUNTAIN_POWER": "4",
        "OCEAN_POWER": "3",
        "RECALL_COST": "3"
    },
    "id": "42GR6RZTWY92CBB4RC9MX4EMTB",
    "imagePath": "https://altered-prod-eu.s3.amazonaws.com/Art/COREKS/CARDS/ALT_CORE_B_BR_12/JPG/en_EN/8b71ecefb88b7524bb1bf122ba003eec.jpg",
    "isSuspended": false,
    "loreEntries": [],
    "lowerPrice": 0,
    "mainFaction": {
        "@id": "/factions/YZ",
        "@type": "Faction",
        "color": "#764891",
        "id": "01GE7AC9WEQKW1Y1BF8SCY7459",
        "name": "Yzmir",
        "reference": "YZ"
    },
    "name": "Hua Mulan",
    "qrUrlDetail": "https://qr.altered.gg/ALT_COREKS_B_BR_12_U_1048",
    "rarity": {
        "@id": "/rarities/UNIQUE",
        "@type": "Rarity",
        "id": "01GE7AC9X35JXEQZJBBD6E4BKW",
        "name": "Unique",
        "reference": "UNIQUE"
    },
    "reference": "ALT_COREKS_B_BR_12_U_1048",
    "translations": {
        "fr-fr": {
            "@context": "/contexts/Card",
            "@id": "/cards/ALT_COREKS_B_BR_12_U_1048",
            "@type": "Card",
            "allImagePath": {
                "de-de": "https://altered-prod-eu.s3.amazonaws.com/Art/COREKS/CARDS/ALT_CORE_B_BR_12/UNIQUE/JPG/de_DE/50e31b0b6566addb1a40c2353b868a11.jpg",
                "en-us": "https://altered-prod-eu.s3.amazonaws.com/Art/COREKS/CARDS/ALT_CORE_B_BR_12/UNIQUE/JPG/en_US/95c041862b1f39955c10527f88fd17ad.jpg",
                "es-es": "https://altered-prod-eu.s3.amazonaws.com/Art/COREKS/CARDS/ALT_CORE_B_BR_12/UNIQUE/JPG/es_ES/f56c7114846926f489cf7f3ab48b48c1.jpg",
                "fr-fr": "https://altered-prod-eu.s3.amazonaws.com/Art/COREKS/CARDS/ALT_CORE_B_BR_12/UNIQUE/JPG/fr_FR/aef78c6c1f744ab16bd8ee07d02ccc69.jpg",
                "it-it": "https://altered-prod-eu.s3.amazonaws.com/Art/COREKS/CARDS/ALT_CORE_B_BR_12/UNIQUE/JPG/it_IT/a5699c3f581021a677b2548b58f6e449.jpg"
            },
            "assets": {
                "WEB": [
                    "https://altered-prod-eu.s3.amazonaws.com/Art/CORE/CARDS/ALT_CORE_B_BR_12/ALT_CORE_B_BR_12_C_WEB.jpg",
                    "https://altered-prod-eu.s3.amazonaws.com/Art/CORE/CARDS/ALT_CORE_B_BR_12/ALT_CORE_B_BR_12_R_WEB.jpg",
                    "https://altered-prod-eu.s3.amazonaws.com/Art/CORE/CARDS/ALT_CORE_B_BR_12/ALT_CORE_B_BR_12_U_WEB.jpg"
                ]
            },
            "cardRulings": [],
            "cardSet": {
                "@id": "/card_sets/COREKS",
                "@type": "CardSet",
                "id": "01HN5TWSSVYM93FHCEC3K8NNCM",
                "name": "Au-delà des portes - Édition KS",
                "reference": "COREKS"
            },
            "cardSubTypes": [
                {
                    "@id": "/.well-known/genid/4f9601261c867fed06bb",
                    "@type": "CardSubType",
                    "id": "01HKAGPC92CGHANVSRSC8R8ES6",
                    "name": "Aventurier",
                    "reference": "ADVENTURER"
                }
            ],
            "cardType": {
                "@id": "/card_types/01H19NWA92A4ERAC4ATMSZNASS",
                "@type": "CardType",
                "id": "01H19NWA92A4ERAC4ATMSZNASS",
                "name": "Personnage",
                "reference": "CHARACTER"
            },
            "elements": {
                "FOREST_POWER": "1",
                "MAIN_COST": "3",
                "MAIN_EFFECT": "{H} Vous pouvez mettre une carte de votre main en Réserve. Si vous le faites : Je gagne 2 boosts.  Au Crépuscule — Si j'ai au moins 1 boost : Je perds [[Fugace]].",
                "MOUNTAIN_POWER": "4",
                "OCEAN_POWER": "3",
                "RECALL_COST": "3"
            },
            "id": "42GR6RZTWY92CBB4RC9MX4EMTB",
            "imagePath": "https://altered-prod-eu.s3.amazonaws.com/Art/COREKS/CARDS/ALT_CORE_B_BR_12/UNIQUE/JPG/fr_FR/aef78c6c1f744ab16bd8ee07d02ccc69.jpg",
            "isSuspended": false,
            "loreEntries": [],
            "lowerPrice": 0,
            "mainFaction": {
                "@id": "/factions/YZ",
                "@type": "Faction",
                "color": "#764891",
                "id": "01GE7AC9WEQKW1Y1BF8SCY7459",
                "name": "Yzmir",
                "reference": "YZ"
            },
            "name": "Hua Mulan",
            "qrUrlDetail": "https://qr.altered.gg/ALT_COREKS_B_BR_12_U_1048",
            "rarity": {
                "@id": "/rarities/UNIQUE",
                "@type": "Rarity",
                "id": "01GE7AC9X35JXEQZJBBD6E4BKW",
                "name": "Unique",
                "reference": "UNIQUE"
            },
            "reference": "ALT_COREKS_B_BR_12_U_1048"
        }
    }
}